jitcsde/__init__.py
jitcsde/_jitcsde.py
jitcsde/_python_core.py
jitcsde/jitced_template.c
jitcsde/random_numbers.c
jitcsde/sympy_symbols.py
jitcsde/version.py
jitcsde-1.6.2.dist-info/licenses/LICENSE
jitcsde-1.6.2.dist-info/METADATA
jitcsde-1.6.2.dist-info/WHEEL
jitcsde-1.6.2.dist-info/top_level.txt
jitcsde-1.6.2.dist-info/RECORD
