Metadata-Version: 2.4
Name: jitcsde
Version: 1.6.2
Summary: Just-in-Time Compilation for Stochastic Differential Equations
Author-email: Gerrit Ansmann <gansmann@uni-bonn.de>
License: BSD-3-Clause
Project-URL: Documentation, https://jitcsde.readthedocs.io
Project-URL: Homepage, http://github.com/neurophysik/jitcsde
Classifier: Development Status :: 4 - Beta
Classifier: License :: OSI Approved :: BSD License
Classifier: Operating System :: POSIX
Classifier: Operating System :: MacOS :: MacOS X
Classifier: Operating System :: Microsoft :: Windows
Classifier: Programming Language :: Python
Classifier: Topic :: Scientific/Engineering :: Mathematics
Requires-Python: >=3.6
License-File: LICENSE
Requires-Dist: jitcxde_common>=1.3
Requires-Dist: numpy
Requires-Dist: symengine>=0.3.1.dev0
Provides-Extra: test
Requires-Dist: jitcode; extra == "test"
Requires-Dist: scipy; extra == "test"
Requires-Dist: sympy; extra == "test"
Dynamic: license-file
